pyfinity/__init__.py
pyfinity/watchmedo.py
pyfinity-0.0.1.dist-info/LICENSE
pyfinity-0.0.1.dist-info/METADATA
pyfinity-0.0.1.dist-info/WHEEL
pyfinity-0.0.1.dist-info/entry_points.txt
pyfinity-0.0.1.dist-info/top_level.txt
pyfinity-0.0.1.dist-info/RECORD
