Metadata-Version: 2.1
Name: pyfinity
Version: 0.0.1
Summary: A tool that makes the python interpreter seamlessly run forever.
Home-page: https://github.com/mahesh-maximus/pyfinity
Author: Mahesh Maximus
Author-email: 
Project-URL: Bug Tracker, https://github.com/mahesh-maximus/pyfinity/issues
Classifier: Programming Language :: Python :: 3
Classifier: License :: OSI Approved :: MIT License
Classifier: Operating System :: OS Independent
Requires-Python: >=3.6
License-File: LICENSE
